aws_credentials/AWS_Creds.py
aws_credentials/CONFIG.json
aws_credentials/Client.py
aws_credentials/__init__.py
aws_credentials/__main__.py
kabbes_aws_credentials-0.9.0.dist-info/LICENSE
kabbes_aws_credentials-0.9.0.dist-info/METADATA
kabbes_aws_credentials-0.9.0.dist-info/WHEEL
kabbes_aws_credentials-0.9.0.dist-info/top_level.txt
kabbes_aws_credentials-0.9.0.dist-info/RECORD
