Metadata-Version: 2.1
Name: kabbes-aws-credentials
Version: 0.9.0
Summary: system for quickly updating AWS credentials and importing them into Python scripts
Home-page: https://pypi.org/project/kabbes-aws-credentials/
Author: James Kabbes
Author-email: james.kabbes@gmail.com
Project-URL: GitHub, https://github.com/jameskabbes/aws_credentials
Project-URL: Documentation, https://jameskabbes.github.io/aws_credentials
Classifier: Programming Language :: Python :: 3
Classifier: License :: OSI Approved :: MIT License
Classifier: Operating System :: OS Independent
Requires-Python: >=3.7
License-File: LICENSE
Requires-Dist: kabbes-py-starter
Requires-Dist: kabbes-parent-class
Requires-Dist: kabbes-dir-ops
Requires-Dist: kabbes-client
